el800/__init__.py
el800/__main__.py
el800/el800.py
el800/el800_window.py
el800/test17.py
el800_control-1.1.4.dist-info/METADATA
el800_control-1.1.4.dist-info/WHEEL
el800_control-1.1.4.dist-info/entry_points.txt
el800_control-1.1.4.dist-info/top_level.txt
el800_control-1.1.4.dist-info/RECORD
