Metadata-Version: 2.1
Name: el800-control
Version: 1.1.4
Summary: el800 export reads from a serial device connected to a EL800 the last read plate and exports it as pdf.
Home-page: https://gitlab.tuwien.ac.at:iap/app/biomimetics/el800-control.git
Author: Richard van Nieuwenhoven
Author-email: richard.nieuwenhoven@tuwien.ac.at
License: UNKNOWN
Project-URL: Homepage, https://gitlab.tuwien.ac.at:iap/app/biomimetics/el800-control.git
Keywords: el800
Platform: UNKNOWN
Classifier: Programming Language :: Python :: 3
Classifier: License :: OSI Approved :: MIT License
Classifier: Operating System :: OS Independent
Requires-Python: >=3.1
Requires-Dist: matplotlib (>=3.5.1)
Requires-Dist: pyserial (>3.3)
Requires-Dist: tk (>=0.1.0)
